{"cameraMode":{"drawMode":0,"name":"Shaded","section":"Shading Mode"},"sceneLighting":true,"audioPlay":false,"sceneViewState":{"m_AlwaysRefresh":false,"showFog":true,"showSkybox":true,"showFlares":true,"showImageEffects":true,"showParticleSystems":true,"showVisualEffectGraphs":true,"m_FxEnabled":true},"in2DMode":false,"pivot":{"x":37.023902893066409,"y":10.167625427246094,"z":30.753551483154298},"rotation":{"x":-0.6685950756072998,"y":0.0015596617013216019,"z":-0.0014019431546330453,"w":-0.7436379790306091},"size":33.88895034790039,"orthographic":false}